django_dunder/__init__.py
django_dunder/_formatter.py
django_dunder/_meta_options.py
django_dunder/_register.py
django_dunder/app_settings.py
django_dunder/apps.py
django_dunder/checks.py
django_dunder/core.py
django_dunder/mixins.py
django_dunder/models.py
django_dunder/tests/__init__.py
django_dunder/tests/conftest.py
django_dunder/tests/test_format.py
django_dunder/tests/test_repr.py
django_dunder/tests/test_settings.py
django_dunder/tests/test_str.py
django_dunder/tests/test_unicode.py
django_dunder-0.3.0.dist-info/LICENSE
django_dunder-0.3.0.dist-info/METADATA
django_dunder-0.3.0.dist-info/WHEEL
django_dunder-0.3.0.dist-info/top_level.txt
django_dunder-0.3.0.dist-info/version.txt
django_dunder-0.3.0.dist-info/RECORD
